rugaming/__init__.py
rugaming/core.py
rugaming/objects.py
rugaming/utils.py
rugaming/ai/__init__.py
rugaming/ai/agents.py
rugaming-2.0.0.dist-info/licenses/LICENSE.txt
rugaming-2.0.0.dist-info/METADATA
rugaming-2.0.0.dist-info/WHEEL
rugaming-2.0.0.dist-info/top_level.txt
rugaming-2.0.0.dist-info/RECORD
